trieve_python_client/__init__.py
trieve_python_client/api/__init__.py
trieve_python_client/api/auth_api.py
trieve_python_client/api/chunk_api.py
trieve_python_client/api/chunk_collection_api.py
trieve_python_client/api/dataset_api.py
trieve_python_client/api/file_api.py
trieve_python_client/api/health_api.py
trieve_python_client/api/invitation_api.py
trieve_python_client/api/message_api.py
trieve_python_client/api/notifications_api.py
trieve_python_client/api/organization_api.py
trieve_python_client/api/stripe_api.py
trieve_python_client/api/topic_api.py
trieve_python_client/api/user_api.py
trieve_python_client/api_client.py
trieve_python_client/api_response.py
trieve_python_client/configuration.py
trieve_python_client/exceptions.py
trieve_python_client/models/__init__.py
trieve_python_client/models/add_chunk_to_collection_data.py
trieve_python_client/models/api_key_dto.py
trieve_python_client/models/auth_data.py
trieve_python_client/models/bookmark_chunks.py
trieve_python_client/models/bookmark_collection_result.py
trieve_python_client/models/bookmark_data.py
trieve_python_client/models/chat_message_proxy.py
trieve_python_client/models/chunk_collection.py
trieve_python_client/models/chunk_collection_and_file.py
trieve_python_client/models/chunk_metadata.py
trieve_python_client/models/chunk_metadata_with_file_data.py
trieve_python_client/models/client_dataset_configuration.py
trieve_python_client/models/collection_data.py
trieve_python_client/models/create_chunk_collection_data.py
trieve_python_client/models/create_chunk_data.py
trieve_python_client/models/create_dataset_request.py
trieve_python_client/models/create_message_data.py
trieve_python_client/models/create_organization_data.py
trieve_python_client/models/create_topic_data.py
trieve_python_client/models/dataset.py
trieve_python_client/models/dataset_and_org_with_sub_and_plan.py
trieve_python_client/models/dataset_and_usage.py
trieve_python_client/models/dataset_dto.py
trieve_python_client-1.0.0.dist-info/METADATA
trieve_python_client-1.0.0.dist-info/WHEEL
trieve_python_client-1.0.0.dist-info/RECORD
